<?xml version="1.0" encoding="UTF-8"?><record_update table="sp_instance">
    <sp_instance action="DELETE">
        <active>true</active>
        <class_name/>
        <color>default</color>
        <css/>
        <glyph/>
        <id/>
        <order>1</order>
        <roles/>
        <short_description/>
        <size>md</size>
        <sp_column display_value="1">0781f188477602107cc7995b116d43ab</sp_column>
        <sp_widget display_value="Selectable Line List">3fd1aae7b74221102452d9fbce11a9ee</sp_widget>
        <sys_class_name>sp_instance</sys_class_name>
        <sys_created_by>admin</sys_created_by>
        <sys_created_on>2024-06-10 05:38:35</sys_created_on>
        <sys_id>92023dc8477602107cc7995b116d43bf</sys_id>
        <sys_mod_count>4</sys_mod_count>
        <sys_name/>
        <sys_package display_value="Loaner Vehicle Request and Inventory" source="x_823134_lva">91ef4311474202107cc7995b116d4346</sys_package>
        <sys_policy/>
        <sys_scope display_value="Loaner Vehicle Request and Inventory">91ef4311474202107cc7995b116d4346</sys_scope>
        <sys_update_name>sp_instance_92023dc8477602107cc7995b116d43bf</sys_update_name>
        <sys_updated_by>admin</sys_updated_by>
        <sys_updated_on>2024-06-10 05:40:01</sys_updated_on>
        <title/>
        <url/>
        <widget_parameters/>
    </sp_instance>
    <sys_translated_text action="DELETE" query="documentkey=92023dc8477602107cc7995b116d43bf"/>
    <sys_update_version action="INSERT_OR_UPDATE">
        <action>DELETE</action>
        <application display_value="Loaner Vehicle Request and Inventory">91ef4311474202107cc7995b116d4346</application>
        <file_path/>
        <instance_id>da9489dc1b8ebd54fe1b43f4bd4bcbf7</instance_id>
        <instance_name>dev189631</instance_name>
        <name>sp_instance_92023dc8477602107cc7995b116d43bf</name>
        <payload><![CDATA[<?xml version="1.0" encoding="UTF-8"?><record_update table="sp_instance"><sp_instance action="INSERT_OR_UPDATE"><active>true</active><class_name/><color>default</color><css/><glyph/><id/><order>1</order><roles/><short_description/><size>md</size><sp_column display_value="1">0781f188477602107cc7995b116d43ab</sp_column><sp_widget display_value="Selectable Line List">3fd1aae7b74221102452d9fbce11a9ee</sp_widget><sys_class_name>sp_instance</sys_class_name><sys_created_by>admin</sys_created_by><sys_created_on>2024-06-10 05:38:35</sys_created_on><sys_id>92023dc8477602107cc7995b116d43bf</sys_id><sys_mod_count>4</sys_mod_count><sys_name/><sys_package display_value="Loaner Vehicle Request and Inventory" source="x_823134_lva">91ef4311474202107cc7995b116d4346</sys_package><sys_policy/><sys_scope display_value="Loaner Vehicle Request and Inventory">91ef4311474202107cc7995b116d4346</sys_scope><sys_update_name>sp_instance_92023dc8477602107cc7995b116d43bf</sys_update_name><sys_updated_by>admin</sys_updated_by><sys_updated_on>2024-06-10 05:40:01</sys_updated_on><title/><url/><widget_parameters/></sp_instance><sys_translated_text action="delete_multiple" query="documentkey=92023dc8477602107cc7995b116d43bf"/></record_update>]]></payload>
        <payload_hash>1457965142</payload_hash>
        <record_name/>
        <reverted_from/>
        <source>f9c21b15474202107cc7995b116d430c</source>
        <source_table>sys_update_set</source_table>
        <state>previous</state>
        <sys_created_by>admin</sys_created_by>
        <sys_created_on>2024-06-10 05:40:01</sys_created_on>
        <sys_id>db52350c477602107cc7995b116d435f</sys_id>
        <sys_mod_count>0</sys_mod_count>
        <sys_recorded_at>19000a91cfe0000001</sys_recorded_at>
        <sys_updated_by>admin</sys_updated_by>
        <sys_updated_on>2024-06-10 05:40:01</sys_updated_on>
        <type>Instance</type>
        <update_guid>9352350c6776021068559e7ac19ac05f</update_guid>
        <update_guid_history>9352350c6776021068559e7ac19ac05f:1457965142,9652f10cd2760210e1bc145f5b3be2df:-69238953,9242b10cb17602101e85a01bba1fe869:-1596443048,d232710c567602105ac26747421a1610:-69238953,96023dc8eb76021085739af31337f0c0:1457965142</update_guid_history>
    </sys_update_version>
    <sys_metadata_delete action="INSERT_OR_UPDATE">
        <sys_audit_delete display_value="">01b5c9dc477642107cc7995b116d43f6</sys_audit_delete>
        <sys_class_name>sys_metadata_delete</sys_class_name>
        <sys_created_by>admin</sys_created_by>
        <sys_created_on>2024-06-10 21:03:22</sys_created_on>
        <sys_db_object display_value="" name="sp_instance">sp_instance</sys_db_object>
        <sys_id>abe9f0bc77844690bf57329da3f33fc9</sys_id>
        <sys_metadata>92023dc8477602107cc7995b116d43bf</sys_metadata>
        <sys_mod_count>0</sys_mod_count>
        <sys_name/>
        <sys_package display_value="Loaner Vehicle Request and Inventory" source="x_823134_lva">91ef4311474202107cc7995b116d4346</sys_package>
        <sys_parent/>
        <sys_policy/>
        <sys_scope display_value="Loaner Vehicle Request and Inventory">91ef4311474202107cc7995b116d4346</sys_scope>
        <sys_scope_delete display_value="">0ff23ab534ee4ac4815c624eef8357e4</sys_scope_delete>
        <sys_update_name>sp_instance_92023dc8477602107cc7995b116d43bf</sys_update_name>
        <sys_update_version display_value="sp_instance_92023dc8477602107cc7995b116d43bf">db52350c477602107cc7995b116d435f</sys_update_version>
        <sys_updated_by>admin</sys_updated_by>
        <sys_updated_on>2024-06-10 21:03:22</sys_updated_on>
    </sys_metadata_delete>
</record_update>
